{
  "requested_url": "https://fins.kdic.or.kr/cm/bbs/selectFaqTop10.do",
  "final_url": "https://fins.kdic.or.kr/cm/bbs/selectFaqTop10.do",
  "status_code": 200,
  "ok": true,
  "content_type": "text/html; charset=UTF-8",
  "encoding": "UTF-8",
  "elapsed_seconds": 0.614,
  "collected_at": "2026-07-16T10:59:04+09:00",
  "content_length": 204719,
  "raw_sha256": "7656bcb49f41c969b2417d851699d3afd8919a09ded96f432f86194f207c18c2",
  "redirect_history": [],
  "selected_headers": {
    "Content-Type": "text/html; charset=UTF-8",
    "Robots-Check": "unavailable:UnicodeDecodeError"
  },
  "url_id": "MT-005",
  "business_function": "착오송금 반환 신청",
  "page_title_manifest": "고객센터 > FAQ > TOP 10",
  "fetch_strategy": "paginated_public",
  "parser_profile": "kdic_final_media_attachment_v2",
  "raw_html_path": "raw/html/착오송금 반환 신청/MT-005.html"
}